Metadata-Version: 1.0
Name: mugan86pkg
Version: 0.1
Summary: Testing installation of Package
Home-page: https://anartz-mugika.com
Author: Anartz Mugika Ledo
Author-email: mugan86@gmail.com
License: MIT
Platform: UNKNOWN
